fact_book/__init__.py
fact_book/admin.py
fact_book/apps.py
fact_book/models.py
fact_book/serializers.py
fact_book/urls.py
fact_book/utils.py
fact_book/views.py
fact_book/management/__init__.py
fact_book/management/commands/__init__.py
fact_book/management/commands/sync.py
fact_book/migrations/0001_initial.py
fact_book/migrations/0002_auto_20160522_1637.py
fact_book/migrations/0003_country_data.py
fact_book/migrations/__init__.py
django_factbook-0.4.0.dist-info/LICENSE
django_factbook-0.4.0.dist-info/METADATA
django_factbook-0.4.0.dist-info/WHEEL
django_factbook-0.4.0.dist-info/top_level.txt
django_factbook-0.4.0.dist-info/RECORD
