Metadata-Version: 2.1
Name: django-factbook
Version: 0.4.0
Summary: A simple Django app to look up facts about the world.
Home-page: http://www.obitec.co.za/
Author: JR Minnaar
Author-email: jr.minnaar+pypi@gmail.com
License: BSD License
Platform: UNKNOWN
Classifier: Environment :: Web Environment
Classifier: Framework :: Django
Classifier: Intended Audience :: Developers
Classifier: License :: OSI Approved :: BSD License
Classifier: Operating System :: OS Independent
Classifier: Programming Language :: Python
Classifier: Programming Language :: Python :: 3
Classifier: Topic :: Internet :: WWW/HTTP
Classifier: Topic :: Internet :: WWW/HTTP :: Dynamic Content
